{
  "LevelData": [{
    "Width": 5,
    "Height": 5,
    "Tiles": [
      "Spawnpoint",
      "Normal",
      "Normal",
      "Normal",
      "Normal",
      "Normal",
      "Normal",
      "Normal",
      "Waypoint",
      "Normal",
      "Normal",
      "Normal",
      "Normal",
      "Normal",
      "Normal",
      "Normal",
      "Normal",
      "Normal",
      "Normal",
      "Normal",
      "Normal",
      "Normal",
      "Normal",
      "Waypoint",
      "Normal"
    ]
  },
    {
      "Width": 3,
      "Height": 3,
      "Tiles": [
        "Waypoint",
        "Normal",
        "Normal",
        "Normal",
        "Normal",
        "Normal",
        "Normal",
        "Normal",
        "Waypoint"
      ]
    }
  ]
}